{
  "id": "wrapper",
  "name": "Wrapper",
  "description": "Conditional wrapper for preserving widget structure.",
  "category": "utility",
  "tier": "primitive",
  "tags": [
    "utility",
    "layout"
  ],
  "dependencies": {
    "shared": [],
    "components": [],
    "pubspec": {}
  },
  "assets": [],
  "fonts": [],
  "files": [
    "_impl/state/wrapper_state.dart",
    "wrapper.dart"
  ],
  "api": {
    "constructors": [],
    "callbacks": [],
    "types": [
      "`Wrapper`",
      "`WrapperBuilder`"
    ]
  },
  "version": "1.0.0"
}
